sortableclasses/__init__.py
sortableclasses-0.9.4.dist-info/LICENSE.txt
sortableclasses-0.9.4.dist-info/METADATA
sortableclasses-0.9.4.dist-info/WHEEL
sortableclasses-0.9.4.dist-info/top_level.txt
sortableclasses-0.9.4.dist-info/RECORD
