Metadata-Version: 2.1
Name: sortableclasses
Version: 0.9.4
Summary: Retrieve all classes derived from a class and
Home-page: https://github.com/odkr/sortableclasses/
Author: Odin Kroeger
Author-email: xacuml@maskr.me
License: GPL
Keywords: plugin
Platform: UNKNOWN
Classifier: Development Status :: 4 - Beta
Classifier: Intended Audience :: Developers
Classifier: License :: OSI Approved :: GNU General Public License v3 or later (GPLv3+)
Classifier: Natural Language :: English
Classifier: Programming Language :: Python :: 3
Classifier: Operating System :: OS Independent
Requires-Python: >=3, <4
